apeman/__init__.py
apeman/dal/__init__.py
apeman/dal/tsdb/__init__.py
apeman/dal/tsdb/data_amount.py
apeman/dal/tsdb/data_type.py
apeman/dal/tsdb/proto_builder.py
apeman/dal/tsdb/proto_builder_test.py
apeman/dal/tsdb/tsdb_client.py
apeman/dal/tsdb/tsdb_pb2.py
apeman/dal/tsdb/tsdb_pb2_grpc.py
apeman_dal_client-0.0.15.dist-info/METADATA
apeman_dal_client-0.0.15.dist-info/WHEEL
apeman_dal_client-0.0.15.dist-info/top_level.txt
apeman_dal_client-0.0.15.dist-info/RECORD
