Metadata-Version: 2.1
Name: apeman-dal-client
Version: 0.0.15
Summary: Apeman DAL service client SDK
Author: nirvana
Author-email: nirvana.blanks@gmail.com
Classifier: Programming Language :: Python :: 3
Classifier: License :: OSI Approved :: MIT License
Classifier: Operating System :: OS Independent
Requires-Python: >=3.7
Requires-Dist: grpcio (==1.51.1)
Requires-Dist: protobuf (==3.20.3)
